BeautifulDatetime/BeautifulDatetime.py
BeautifulDatetime/__init__.py
BeautifulDatetime/__version__.py
BeautifulDatetime-1.0.0.dist-info/LICENSE
BeautifulDatetime-1.0.0.dist-info/METADATA
BeautifulDatetime-1.0.0.dist-info/WHEEL
BeautifulDatetime-1.0.0.dist-info/top_level.txt
BeautifulDatetime-1.0.0.dist-info/RECORD
