Metadata-Version: 2.1
Name: BeautifulDatetime
Version: 1.0.0
Summary: 日期时间友好处理小工具。
Home-page: https://github.com/SombreKnight/BeautifulDatetime
Author: SombreKnight
Author-email: 517736825@qq.com
License: MIT
Platform: UNKNOWN
Classifier: License :: OSI Approved :: MIT License
Classifier: Programming Language :: Python
Classifier: Programming Language :: Python :: 3
Classifier: Programming Language :: Python :: 3.6
Classifier: Programming Language :: Python :: Implementation :: CPython
Classifier: Programming Language :: Python :: Implementation :: PyPy
Requires-Python: >=2.0.0
